streamlit_pdf/__init__.py
streamlit_pdf/pyproject.toml
streamlit_pdf/frontend/build/assets/index-BJ6LuR10.js
streamlit_pdf/frontend/build/assets/index-IrMyiucU.css
streamlit_pdf/frontend/build/assets/cmaps/78-EUC-H.bcmap
streamlit_pdf/frontend/build/assets/cmaps/78-EUC-V.bcmap
streamlit_pdf/frontend/build/assets/cmaps/78-H.bcmap
streamlit_pdf/frontend/build/assets/cmaps/78-RKSJ-H.bcmap
streamlit_pdf/frontend/build/assets/cmaps/78-RKSJ-V.bcmap
streamlit_pdf/frontend/build/assets/cmaps/78-V.bcmap
streamlit_pdf/frontend/build/assets/cmaps/78ms-RKSJ-H.bcmap
streamlit_pdf/frontend/build/assets/cmaps/78ms-RKSJ-V.bcmap
streamlit_pdf/frontend/build/assets/cmaps/83pv-RKSJ-H.bcmap
streamlit_pdf/frontend/build/assets/cmaps/90ms-RKSJ-H.bcmap
streamlit_pdf/frontend/build/assets/cmaps/90ms-RKSJ-V.bcmap
streamlit_pdf/frontend/build/assets/cmaps/90msp-RKSJ-H.bcmap
streamlit_pdf/frontend/build/assets/cmaps/90msp-RKSJ-V.bcmap
streamlit_pdf/frontend/build/assets/cmaps/90pv-RKSJ-H.bcmap
streamlit_pdf/frontend/build/assets/cmaps/90pv-RKSJ-V.bcmap
streamlit_pdf/frontend/build/assets/cmaps/Add-H.bcmap
streamlit_pdf/frontend/build/assets/cmaps/Add-RKSJ-H.bcmap
streamlit_pdf/frontend/build/assets/cmaps/Add-RKSJ-V.bcmap
streamlit_pdf/frontend/build/assets/cmaps/Add-V.bcmap
streamlit_pdf/frontend/build/assets/cmaps/Adobe-CNS1-0.bcmap
streamlit_pdf/frontend/build/assets/cmaps/Adobe-CNS1-1.bcmap
streamlit_pdf/frontend/build/assets/cmaps/Adobe-CNS1-2.bcmap
streamlit_pdf/frontend/build/assets/cmaps/Adobe-CNS1-3.bcmap
streamlit_pdf/frontend/build/assets/cmaps/Adobe-CNS1-4.bcmap
streamlit_pdf/frontend/build/assets/cmaps/Adobe-CNS1-5.bcmap
streamlit_pdf/frontend/build/assets/cmaps/Adobe-CNS1-6.bcmap
streamlit_pdf/frontend/build/assets/cmaps/Adobe-CNS1-UCS2.bcmap
streamlit_pdf/frontend/build/assets/cmaps/Adobe-GB1-0.bcmap
streamlit_pdf/frontend/build/assets/cmaps/Adobe-GB1-1.bcmap
streamlit_pdf/frontend/build/assets/cmaps/Adobe-GB1-2.bcmap
streamlit_pdf/frontend/build/assets/cmaps/Adobe-GB1-3.bcmap
streamlit_pdf-2.0.0.dist-info/licenses/LICENSE
streamlit_pdf-2.0.0.dist-info/licenses/NOTICES
streamlit_pdf-2.0.0.dist-info/METADATA
streamlit_pdf-2.0.0.dist-info/WHEEL
streamlit_pdf-2.0.0.dist-info/top_level.txt
streamlit_pdf-2.0.0.dist-info/RECORD
