Metadata-Version: 2.4
Name: streamlit-pdf
Version: 2.0.0
Summary: A Streamlit component for viewing PDF files
Author-email: Snowflake Inc <hello@streamlit.io>
Maintainer-email: Snowflake Inc <hello@streamlit.io>
License-Expression: Apache-2.0
Project-URL: Homepage, https://streamlit.io
Project-URL: Source Code, https://github.com/streamlit/streamlit-pdf
Project-URL: Bug Tracker, https://github.com/streamlit/streamlit/issues
Project-URL: Community, https://discuss.streamlit.io/
Project-URL: Twitter, https://twitter.com/streamlit
Keywords: streamlit,pdf,viewer,react,component
Classifier: Development Status :: 3 - Alpha
Classifier: Intended Audience :: Developers
Classifier: Programming Language :: Python :: 3
Classifier: Programming Language :: Python :: 3.9
Classifier: Programming Language :: Python :: 3.10
Classifier: Programming Language :: Python :: 3.11
Classifier: Programming Language :: Python :: 3.12
Classifier: Topic :: Software Development :: Libraries :: Python Modules
Classifier: Topic :: Office/Business :: Office Suites
Classifier: Topic :: Multimedia :: Graphics :: Viewers
Requires-Python: >=3.9
License-File: LICENSE
License-File: NOTICES
Provides-Extra: devel
Requires-Dist: wheel; extra == "devel"
Requires-Dist: pytest==7.4.0; extra == "devel"
Requires-Dist: playwright==1.49.*; extra == "devel"
Requires-Dist: requests==2.31.0; extra == "devel"
Requires-Dist: pytest-playwright-snapshot==1.0; extra == "devel"
Requires-Dist: pytest-rerunfailures==12.0; extra == "devel"
Provides-Extra: with-streamlit
Requires-Dist: streamlit>=1.51.0; extra == "with-streamlit"
Dynamic: license-file
